lingkar33423322/__init__.py
lingkar33423322/lingkar.py
lingkar33423322-7.0.dist-info/LICENSE
lingkar33423322-7.0.dist-info/METADATA
lingkar33423322-7.0.dist-info/WHEEL
lingkar33423322-7.0.dist-info/top_level.txt
lingkar33423322-7.0.dist-info/RECORD
