Metadata-Version: 2.1
Name: lingkar33423322
Version: 7.0
Summary: Menghitung luas lingkaran
Home-page: https://github.com/SabillillahX/lingkar.git
Author: SabillillahX
Author-email: <sabillillahxtkj@gmail.com>
License: MIT
Keywords: luas,lingkaran
Classifier: Development Status :: 1 - Planning
License-File: LICENSE
